[
{
"ShapeId": 5,
"TrackerId": 0,
"ShapeType": "Square",
"ShapeDimensions": [471, 260, 100],
"PenColor": "black",
"PenWidth": 1,
"PenStyle": "SolidLine",
"PenCapStyle": "SquareCap",
"PenJoinStyle": "BevelJoin",
"BrushColor": "black",
"BrushStyle": "NoBrush"
},
{
"ShapeId": 1,
"TrackerId": 1,
"ShapeType": "Line",
"ShapeDimensions": [115, 439, 165, 489],
"PenColor": "black",
"PenWidth": 1,
"PenStyle": "SolidLine",
"PenCapStyle": "SquareCap",
"PenJoinStyle": "BevelJoin"
},
{
"ShapeId": 3,
"TrackerId": 2,
"ShapeType": "Polygon",
"ShapeDimensions": [246, 293, 296, 243, 346, 293, 296, 278],
"PenColor": "black",
"PenWidth": 1,
"PenStyle": "SolidLine",
"PenCapStyle": "SquareCap",
"PenJoinStyle": "BevelJoin",
"BrushColor": "black",
"BrushStyle": "NoBrush"
},
{
"ShapeId": 4,
"TrackerId": 3,
"ShapeType": "Rectangle",
"ShapeDimensions": [545, 139, 100, 50],
"PenColor": "black",
"PenWidth": 1,
"PenStyle": "SolidLine",
"PenCapStyle": "SquareCap",
"PenJoinStyle": "BevelJoin",
"BrushColor": "black",
"BrushStyle": "NoBrush"
},
{
"ShapeId": 2,
"TrackerId": 4,
"ShapeType": "Polyline",
"ShapeDimensions": [433, 674, 458, 624, 483, 674, 508, 624],
"PenColor": "black",
"PenWidth": 1,
"PenStyle": "SolidLine",
"PenCapStyle": "SquareCap",
"PenJoinStyle": "BevelJoin"
}
]
